transmits/__init__.py
transmits/transmits.py
transmits-0.1.4.dist-info/LICENSE
transmits-0.1.4.dist-info/METADATA
transmits-0.1.4.dist-info/WHEEL
transmits-0.1.4.dist-info/top_level.txt
transmits-0.1.4.dist-info/RECORD
