Metadata-Version: 2.1
Name: transmits
Version: 0.1.4
Summary: A package to transmit data
Author-email: Gu waakzi <guwaakzi@gmail.com>
License: MIT License
Project-URL: url, https://github.com/Guwaakzi/transmits
Classifier: License :: OSI Approved :: MIT License
Classifier: Programming Language :: Python :: 3
Classifier: Programming Language :: Python :: 3.6
Classifier: Programming Language :: Python :: 3.7
Classifier: Programming Language :: Python :: 3.8
Classifier: Programming Language :: Python :: 3.9
Classifier: Programming Language :: Python :: 3.10
Requires-Python: >=3.6
License-File: LICENSE
